Metadata-Version: 1.1
Name: pandoc-latex-barcode
Version: 1.1.1
Summary: A pandoc filter to insert barcodes and QR codes in a latex/pdf document
Home-page: https://github.com/daamien/pandoc-latex-barcode
Author: Damien Clochard
Author-email: daamien@gmail.com
License: BSD
Download-URL: https://github.com/daamien/pandoc-latex-barcode/archive/master.zip
Keywords: pandoc,filters,latex,barcode,qrcode
Platform: UNKNOWN
Classifier: Development Status :: 5 - Production/Stable
Classifier: Operating System :: OS Independent
Classifier: Environment :: Console
Classifier: Intended Audience :: End Users/Desktop
Classifier: Intended Audience :: Developers
Classifier: Topic :: Software Development :: Build Tools
Classifier: Topic :: Software Development :: Documentation
Classifier: Topic :: Text Processing :: Filters
Classifier: Programming Language :: Python :: 2.7
Classifier: Programming Language :: Python :: 3.3
Classifier: Programming Language :: Python :: 3.4
Classifier: Programming Language :: Python :: 3.5
